main.py
server.py
tools/__init__.py
tools/answer_patient_queries.py
utils/__init__.py
utils/llm_call.py
ho_rag-1.0.0.dist-info/METADATA
ho_rag-1.0.0.dist-info/WHEEL
ho_rag-1.0.0.dist-info/entry_points.txt
ho_rag-1.0.0.dist-info/top_level.txt
ho_rag-1.0.0.dist-info/RECORD
