Metadata-Version: 2.4
Name: ho-rag
Version: 1.0.0
Summary: Add your description here
Requires-Python: >=3.12
Requires-Dist: dotenv>=0.9.9
Requires-Dist: mcp[cli]>=1.6.0
Requires-Dist: motor>=3.7.1
Requires-Dist: tenacity>=9.1.2
